sphinxext/linkcheckdiff.py
sphinxext_linkcheckdiff-0.1.0.dist-info/LICENSE.md
sphinxext_linkcheckdiff-0.1.0.dist-info/METADATA
sphinxext_linkcheckdiff-0.1.0.dist-info/WHEEL
sphinxext_linkcheckdiff-0.1.0.dist-info/top_level.txt
sphinxext_linkcheckdiff-0.1.0.dist-info/RECORD
