Metadata-Version: 2.1
Name: sphinxext-linkcheckdiff
Version: 0.1.0
Summary: Sphinx Extension to run diff-only linkchecks
Home-page: https://github.com/wpilibsuite/sphinxext-linkcheckdiff
Author: Vasista Vovveti
Author-email: vasistavovveti@gmail.com
License: UNKNOWN
Platform: UNKNOWN
Classifier: Environment :: Plugins
Classifier: Environment :: Web Environment
Classifier: Framework :: Sphinx :: Extension
Classifier: Intended Audience :: Developers
Classifier: License :: OSI Approved :: MIT License
Classifier: Natural Language :: English
Classifier: Operating System :: OS Independent
Classifier: Programming Language :: Python :: 3.6
Classifier: Programming Language :: Python :: 3.7
Classifier: Programming Language :: Python :: 3.8
Classifier: Programming Language :: Python
Classifier: Topic :: Documentation :: Sphinx
Classifier: Topic :: Documentation
Classifier: Topic :: Software Development :: Documentation
Classifier: Topic :: Text Processing
Classifier: Topic :: Utilities
Requires-Python: >=3.6
Requires-Dist: sphinx (>=3.0)
